{
  "updated_at": "2026-07-13T08:58:07+09:00",
  "stocks": [
    {
      "id": "inpex",
      "name": "INPEX",
      "name_ja": "INPEX",
      "sector": "エネルギー",
      "macro_pairs": [
        "wti",
        "brent"
      ],
      "description": "原油・天然ガス開発。WTI/ブレント原油と強く連動する傾向。",
      "category": "portfolio",
      "value": 3361.0,
      "change": -66.0,
      "change_pct": -1.93,
      "week_pct": 1.57,
      "month_pct": -4.02,
      "history": [
        {
          "date": "2026-06-01",
          "close": 3360.9526
        },
        {
          "date": "2026-06-02",
          "close": 3509.5193
        },
        {
          "date": "2026-06-03",
          "close": 3647.2632
        },
        {
          "date": "2026-06-04",
          "close": 3589.2139
        },
        {
          "date": "2026-06-05",
          "close": 3625.6177
        },
        {
          "date": "2026-06-08",
          "close": 3582.3267
        },
        {
          "date": "2026-06-09",
          "close": 3534.1165
        },
        {
          "date": "2026-06-10",
          "close": 3426.8728
        },
        {
          "date": "2026-06-11",
          "close": 3548.8748
        },
        {
          "date": "2026-06-12",
          "close": 3501.6482
        },
        {
          "date": "2026-06-15",
          "close": 3438.6794
        },
        {
          "date": "2026-06-16",
          "close": 3323.5649
        },
        {
          "date": "2026-06-17",
          "close": 3351.1138
        },
        {
          "date": "2026-06-18",
          "close": 3373.7432
        },
        {
          "date": "2026-06-19",
          "close": 3443.5989
        },
        {
          "date": "2026-06-22",
          "close": 3392.4368
        },
        {
          "date": "2026-06-23",
          "close": 3400.3079
        },
        {
          "date": "2026-06-24",
          "close": 3346.1943
        },
        {
          "date": "2026-06-25",
          "close": 3234.0312
        },
        {
          "date": "2026-06-26",
          "close": 3297.0
        },
        {
          "date": "2026-06-29",
          "close": 3278.0
        },
        {
          "date": "2026-06-30",
          "close": 3265.0
        },
        {
          "date": "2026-07-01",
          "close": 3205.0
        },
        {
          "date": "2026-07-02",
          "close": 3204.0
        },
        {
          "date": "2026-07-03",
          "close": 3242.0
        },
        {
          "date": "2026-07-06",
          "close": 3309.0
        },
        {
          "date": "2026-07-07",
          "close": 3281.0
        },
        {
          "date": "2026-07-08",
          "close": 3388.0
        },
        {
          "date": "2026-07-09",
          "close": 3427.0
        },
        {
          "date": "2026-07-10",
          "close": 3361.0
        }
      ]
    },
    {
      "id": "nintendo",
      "name": "Nintendo",
      "name_ja": "任天堂",
      "sector": "ゲーム・娯楽",
      "macro_pairs": [
        "usdjpy",
        "nasdaq100"
      ],
      "description": "海外売上比率が高くドル円の影響を受けやすい。NASDAQ100との連動も参考に。",
      "category": "portfolio",
      "value": 7030.0,
      "change": -90.0,
      "change_pct": -1.26,
      "week_pct": -0.04,
      "month_pct": -2.01,
      "history": [
        {
          "date": "2026-06-01",
          "close": 7163.0
        },
        {
          "date": "2026-06-02",
          "close": 7426.0
        },
        {
          "date": "2026-06-03",
          "close": 7457.0
        },
        {
          "date": "2026-06-04",
          "close": 7272.0
        },
        {
          "date": "2026-06-05",
          "close": 7524.0
        },
        {
          "date": "2026-06-08",
          "close": 7640.0
        },
        {
          "date": "2026-06-09",
          "close": 7738.0
        },
        {
          "date": "2026-06-10",
          "close": 7215.0
        },
        {
          "date": "2026-06-11",
          "close": 7144.0
        },
        {
          "date": "2026-06-12",
          "close": 7174.0
        },
        {
          "date": "2026-06-15",
          "close": 7110.0
        },
        {
          "date": "2026-06-16",
          "close": 7218.0
        },
        {
          "date": "2026-06-17",
          "close": 7275.0
        },
        {
          "date": "2026-06-18",
          "close": 7166.0
        },
        {
          "date": "2026-06-19",
          "close": 7076.0
        },
        {
          "date": "2026-06-22",
          "close": 7000.0
        },
        {
          "date": "2026-06-23",
          "close": 6917.0
        },
        {
          "date": "2026-06-24",
          "close": 6858.0
        },
        {
          "date": "2026-06-25",
          "close": 6859.0
        },
        {
          "date": "2026-06-26",
          "close": 6589.0
        },
        {
          "date": "2026-06-29",
          "close": 6935.0
        },
        {
          "date": "2026-06-30",
          "close": 6815.0
        },
        {
          "date": "2026-07-01",
          "close": 6980.0
        },
        {
          "date": "2026-07-02",
          "close": 7137.0
        },
        {
          "date": "2026-07-03",
          "close": 7132.0
        },
        {
          "date": "2026-07-06",
          "close": 7033.0
        },
        {
          "date": "2026-07-07",
          "close": 7148.0
        },
        {
          "date": "2026-07-08",
          "close": 7085.0
        },
        {
          "date": "2026-07-09",
          "close": 7120.0
        },
        {
          "date": "2026-07-10",
          "close": 7030.0
        }
      ]
    },
    {
      "id": "shift",
      "name": "SHIFT",
      "name_ja": "SHIFT",
      "sector": "IT・ソフトウェア",
      "macro_pairs": [
        "us10y",
        "nasdaq100"
      ],
      "description": "グロース株。米長期金利上昇局面でバリュエーション圧縮リスクあり。",
      "category": "portfolio",
      "value": 676.5,
      "change": -10.1,
      "change_pct": -1.47,
      "week_pct": -1.11,
      "month_pct": 4.83,
      "history": [
        {
          "date": "2026-06-01",
          "close": 727.2
        },
        {
          "date": "2026-06-02",
          "close": 791.3
        },
        {
          "date": "2026-06-03",
          "close": 694.7
        },
        {
          "date": "2026-06-04",
          "close": 692.6
        },
        {
          "date": "2026-06-05",
          "close": 722.3
        },
        {
          "date": "2026-06-08",
          "close": 685.2
        },
        {
          "date": "2026-06-09",
          "close": 667.6
        },
        {
          "date": "2026-06-10",
          "close": 675.2
        },
        {
          "date": "2026-06-11",
          "close": 678.7
        },
        {
          "date": "2026-06-12",
          "close": 645.3
        },
        {
          "date": "2026-06-15",
          "close": 636.8
        },
        {
          "date": "2026-06-16",
          "close": 637.7
        },
        {
          "date": "2026-06-17",
          "close": 645.0
        },
        {
          "date": "2026-06-18",
          "close": 645.2
        },
        {
          "date": "2026-06-19",
          "close": 631.7
        },
        {
          "date": "2026-06-22",
          "close": 621.1
        },
        {
          "date": "2026-06-23",
          "close": 610.1
        },
        {
          "date": "2026-06-24",
          "close": 616.3
        },
        {
          "date": "2026-06-25",
          "close": 614.0
        },
        {
          "date": "2026-06-26",
          "close": 617.0
        },
        {
          "date": "2026-06-29",
          "close": 672.9
        },
        {
          "date": "2026-06-30",
          "close": 674.0
        },
        {
          "date": "2026-07-01",
          "close": 638.5
        },
        {
          "date": "2026-07-02",
          "close": 684.9
        },
        {
          "date": "2026-07-03",
          "close": 708.5
        },
        {
          "date": "2026-07-06",
          "close": 684.1
        },
        {
          "date": "2026-07-07",
          "close": 705.9
        },
        {
          "date": "2026-07-08",
          "close": 678.9
        },
        {
          "date": "2026-07-09",
          "close": 686.6
        },
        {
          "date": "2026-07-10",
          "close": 676.5
        }
      ]
    },
    {
      "id": "nsc",
      "name": "Nippon Steel",
      "name_ja": "日本製鉄",
      "sector": "素材・鉄鋼",
      "macro_pairs": [
        "wti",
        "usdjpy"
      ],
      "description": "素材・景気敏感株。中国需要・原材料費・ドル円が業績に影響。",
      "category": "portfolio",
      "value": 550.2,
      "change": -5.8,
      "change_pct": -1.04,
      "week_pct": -1.57,
      "month_pct": -0.25,
      "history": [
        {
          "date": "2026-06-01",
          "close": 549.6
        },
        {
          "date": "2026-06-02",
          "close": 536.6
        },
        {
          "date": "2026-06-03",
          "close": 546.7
        },
        {
          "date": "2026-06-04",
          "close": 540.5
        },
        {
          "date": "2026-06-05",
          "close": 547.0
        },
        {
          "date": "2026-06-08",
          "close": 538.8
        },
        {
          "date": "2026-06-09",
          "close": 540.8
        },
        {
          "date": "2026-06-10",
          "close": 542.3
        },
        {
          "date": "2026-06-11",
          "close": 535.0
        },
        {
          "date": "2026-06-12",
          "close": 551.6
        },
        {
          "date": "2026-06-15",
          "close": 574.2
        },
        {
          "date": "2026-06-16",
          "close": 566.0
        },
        {
          "date": "2026-06-17",
          "close": 557.5
        },
        {
          "date": "2026-06-18",
          "close": 565.4
        },
        {
          "date": "2026-06-19",
          "close": 559.8
        },
        {
          "date": "2026-06-22",
          "close": 562.3
        },
        {
          "date": "2026-06-23",
          "close": 551.0
        },
        {
          "date": "2026-06-24",
          "close": 547.2
        },
        {
          "date": "2026-06-25",
          "close": 547.0
        },
        {
          "date": "2026-06-26",
          "close": 543.3
        },
        {
          "date": "2026-06-29",
          "close": 546.1
        },
        {
          "date": "2026-06-30",
          "close": 536.1
        },
        {
          "date": "2026-07-01",
          "close": 531.0
        },
        {
          "date": "2026-07-02",
          "close": 542.0
        },
        {
          "date": "2026-07-03",
          "close": 548.2
        },
        {
          "date": "2026-07-06",
          "close": 559.0
        },
        {
          "date": "2026-07-07",
          "close": 560.3
        },
        {
          "date": "2026-07-08",
          "close": 556.0
        },
        {
          "date": "2026-07-09",
          "close": 556.0
        },
        {
          "date": "2026-07-10",
          "close": 550.2
        }
      ]
    },
    {
      "id": "mitsui",
      "name": "Mitsui & Co.",
      "name_ja": "三井物産",
      "sector": "商社",
      "macro_pairs": [
        "wti",
        "gold"
      ],
      "description": "総合商社。コモディティ全般（資源・エネルギー・金属）と連動。",
      "category": "portfolio",
      "value": 4556.0,
      "change": -58.0,
      "change_pct": -1.26,
      "week_pct": -2.38,
      "month_pct": -6.75,
      "history": [
        {
          "date": "2026-06-01",
          "close": 5033.0
        },
        {
          "date": "2026-06-02",
          "close": 5066.0
        },
        {
          "date": "2026-06-03",
          "close": 5059.0
        },
        {
          "date": "2026-06-04",
          "close": 5041.0
        },
        {
          "date": "2026-06-05",
          "close": 5039.0
        },
        {
          "date": "2026-06-08",
          "close": 4932.0
        },
        {
          "date": "2026-06-09",
          "close": 4931.0
        },
        {
          "date": "2026-06-10",
          "close": 4849.0
        },
        {
          "date": "2026-06-11",
          "close": 4857.0
        },
        {
          "date": "2026-06-12",
          "close": 4886.0
        },
        {
          "date": "2026-06-15",
          "close": 4838.0
        },
        {
          "date": "2026-06-16",
          "close": 4703.0
        },
        {
          "date": "2026-06-17",
          "close": 4719.0
        },
        {
          "date": "2026-06-18",
          "close": 4719.0
        },
        {
          "date": "2026-06-19",
          "close": 4716.0
        },
        {
          "date": "2026-06-22",
          "close": 4739.0
        },
        {
          "date": "2026-06-23",
          "close": 4672.0
        },
        {
          "date": "2026-06-24",
          "close": 4596.0
        },
        {
          "date": "2026-06-25",
          "close": 4446.0
        },
        {
          "date": "2026-06-26",
          "close": 4508.0
        },
        {
          "date": "2026-06-29",
          "close": 4513.0
        },
        {
          "date": "2026-06-30",
          "close": 4497.0
        },
        {
          "date": "2026-07-01",
          "close": 4440.0
        },
        {
          "date": "2026-07-02",
          "close": 4551.0
        },
        {
          "date": "2026-07-03",
          "close": 4600.0
        },
        {
          "date": "2026-07-06",
          "close": 4667.0
        },
        {
          "date": "2026-07-07",
          "close": 4677.0
        },
        {
          "date": "2026-07-08",
          "close": 4657.0
        },
        {
          "date": "2026-07-09",
          "close": 4614.0
        },
        {
          "date": "2026-07-10",
          "close": 4556.0
        }
      ]
    },
    {
      "id": "gmo_pg",
      "name": "GMO Payment Gateway",
      "name_ja": "GMOペイメントGW",
      "sector": "フィンテック",
      "macro_pairs": [
        "us10y",
        "nasdaq100"
      ],
      "description": "グロース・フィンテック株。金利敏感。NASDAQ100との連動を確認。",
      "category": "portfolio",
      "value": 9753.0,
      "change": 128.0,
      "change_pct": 1.33,
      "week_pct": 0.2,
      "month_pct": 17.68,
      "history": [
        {
          "date": "2026-06-01",
          "close": 9069.0
        },
        {
          "date": "2026-06-02",
          "close": 8751.0
        },
        {
          "date": "2026-06-03",
          "close": 8500.0
        },
        {
          "date": "2026-06-04",
          "close": 7900.0
        },
        {
          "date": "2026-06-05",
          "close": 8007.0
        },
        {
          "date": "2026-06-08",
          "close": 7987.0
        },
        {
          "date": "2026-06-09",
          "close": 7992.0
        },
        {
          "date": "2026-06-10",
          "close": 7841.0
        },
        {
          "date": "2026-06-11",
          "close": 8205.0
        },
        {
          "date": "2026-06-12",
          "close": 8288.0
        },
        {
          "date": "2026-06-15",
          "close": 8203.0
        },
        {
          "date": "2026-06-16",
          "close": 8329.0
        },
        {
          "date": "2026-06-17",
          "close": 8373.0
        },
        {
          "date": "2026-06-18",
          "close": 8649.0
        },
        {
          "date": "2026-06-19",
          "close": 8247.0
        },
        {
          "date": "2026-06-22",
          "close": 8058.0
        },
        {
          "date": "2026-06-23",
          "close": 8025.0
        },
        {
          "date": "2026-06-24",
          "close": 8115.0
        },
        {
          "date": "2026-06-25",
          "close": 8277.0
        },
        {
          "date": "2026-06-26",
          "close": 8904.0
        },
        {
          "date": "2026-06-29",
          "close": 9250.0
        },
        {
          "date": "2026-06-30",
          "close": 9280.0
        },
        {
          "date": "2026-07-01",
          "close": 9093.0
        },
        {
          "date": "2026-07-02",
          "close": 9509.0
        },
        {
          "date": "2026-07-03",
          "close": 9720.0
        },
        {
          "date": "2026-07-06",
          "close": 9734.0
        },
        {
          "date": "2026-07-07",
          "close": 10005.0
        },
        {
          "date": "2026-07-08",
          "close": 9955.0
        },
        {
          "date": "2026-07-09",
          "close": 9625.0
        },
        {
          "date": "2026-07-10",
          "close": 9753.0
        }
      ]
    },
    {
      "id": "sanix",
      "name": "Sanix HD",
      "name_ja": "サニックスHD",
      "sector": "環境・エネルギー",
      "macro_pairs": [
        "natgas",
        "wti"
      ],
      "description": "太陽光・環境事業。エネルギー価格と再エネ普及速度が業績に影響。",
      "category": "portfolio",
      "value": 249.0,
      "change": 5.0,
      "change_pct": 2.05,
      "week_pct": -0.4,
      "month_pct": 10.67,
      "history": [
        {
          "date": "2026-06-01",
          "close": 240.0
        },
        {
          "date": "2026-06-02",
          "close": 246.0
        },
        {
          "date": "2026-06-03",
          "close": 247.0
        },
        {
          "date": "2026-06-04",
          "close": 237.0
        },
        {
          "date": "2026-06-05",
          "close": 241.0
        },
        {
          "date": "2026-06-08",
          "close": 236.0
        },
        {
          "date": "2026-06-09",
          "close": 225.0
        },
        {
          "date": "2026-06-10",
          "close": 226.0
        },
        {
          "date": "2026-06-11",
          "close": 223.0
        },
        {
          "date": "2026-06-12",
          "close": 225.0
        },
        {
          "date": "2026-06-15",
          "close": 226.0
        },
        {
          "date": "2026-06-16",
          "close": 223.0
        },
        {
          "date": "2026-06-17",
          "close": 226.0
        },
        {
          "date": "2026-06-18",
          "close": 224.0
        },
        {
          "date": "2026-06-19",
          "close": 222.0
        },
        {
          "date": "2026-06-22",
          "close": 225.0
        },
        {
          "date": "2026-06-23",
          "close": 221.0
        },
        {
          "date": "2026-06-24",
          "close": 221.0
        },
        {
          "date": "2026-06-25",
          "close": 226.0
        },
        {
          "date": "2026-06-26",
          "close": 227.0
        },
        {
          "date": "2026-06-29",
          "close": 229.0
        },
        {
          "date": "2026-06-30",
          "close": 228.0
        },
        {
          "date": "2026-07-01",
          "close": 228.0
        },
        {
          "date": "2026-07-02",
          "close": 234.0
        },
        {
          "date": "2026-07-03",
          "close": 241.0
        },
        {
          "date": "2026-07-06",
          "close": 250.0
        },
        {
          "date": "2026-07-07",
          "close": 248.0
        },
        {
          "date": "2026-07-08",
          "close": 245.0
        },
        {
          "date": "2026-07-09",
          "close": 244.0
        },
        {
          "date": "2026-07-10",
          "close": 249.0
        }
      ]
    }
  ]
}